chrome_switcher/__init__.py
chrome_switcher/advanced_cursor.py
chrome_switcher/browser_path.py
chrome_switcher/browsers.py
chrome_switcher/common.py
chrome_switcher/delete_lnk.py
chrome_switcher/main.py
chrome_switcher/settings.py
chrome_switcher/shortcut.py
chrome_switcher/temp_browser_helper.py
chrome_switcher/scripts/C#/OpenTempChrome/OpenTempChrome.sln
chrome_switcher/scripts/C#/OpenTempChrome/OpenTempChrome/App.config
chrome_switcher/scripts/C#/OpenTempChrome/OpenTempChrome/OpenTempChrome.csproj
chrome_switcher/scripts/C#/OpenTempChrome/OpenTempChrome/Program.cs
chrome_switcher/scripts/C#/OpenTempChrome/OpenTempChrome/Properties/AssemblyInfo.cs
chrome_switcher/scripts/C#/OpenTempChrome/OpenTempChrome/bin/Debug/OpenTempChrome.exe
chrome_switcher/scripts/C#/OpenTempChrome/OpenTempChrome/bin/Debug/OpenTempChrome.exe.config
chrome_switcher/scripts/C#/OpenTempChrome/OpenTempChrome/bin/Debug/OpenTempChrome.pdb
chrome_switcher/scripts/C#/OpenTempChrome/OpenTempChrome/bin/Release/OpenTempChrome.exe
chrome_switcher/scripts/C#/OpenTempChrome/OpenTempChrome/bin/Release/OpenTempChrome.exe.config
chrome_switcher/scripts/C#/OpenTempChrome/OpenTempChrome/bin/Release/OpenTempChrome.pdb
"chrome_switcher/scripts/C#/OpenTempChrome/OpenTempChrome/obj/Debug/.NETFramework,Version=v4.8.AssemblyAttributes.cs"
chrome_switcher/scripts/C#/OpenTempChrome/OpenTempChrome/obj/Debug/DesignTimeResolveAssemblyReferences.cache
chrome_switcher/scripts/C#/OpenTempChrome/OpenTempChrome/obj/Debug/DesignTimeResolveAssemblyReferencesInput.cache
chrome_switcher/scripts/C#/OpenTempChrome/OpenTempChrome/obj/Debug/OpenTempChrome.csproj.CoreCompileInputs.cache
chrome_switcher/scripts/C#/OpenTempChrome/OpenTempChrome/obj/Debug/OpenTempChrome.exe
chrome_switcher/scripts/C#/OpenTempChrome/OpenTempChrome/obj/Debug/OpenTempChrome.pdb
chrome_switcher/scripts/C#/OpenTempChrome/OpenTempChrome/obj/Release/DesignTimeResolveAssemblyReferencesInput.cache
chrome_switcher-0.0.3.dist-info/METADATA
chrome_switcher-0.0.3.dist-info/WHEEL
chrome_switcher-0.0.3.dist-info/entry_points.txt
chrome_switcher-0.0.3.dist-info/licenses/LICENSE
chrome_switcher-0.0.3.dist-info/RECORD
