Metadata-Version: 2.1
Name: chrome-switcher
Version: 0.0.3
Summary: Easily create and load new Chrome profiles
Project-URL: Homepage, https://github.com/pilgrimtabby/chrome-switcher
Project-URL: Issues, https://github.com/pilgrimtabby/chrome-switcher/issues
Author-email: pilgrim_tabby <pilgrimtabby@gmail.com>
License-File: LICENSE
Classifier: License :: OSI Approved :: BSD License
Classifier: Operating System :: MacOS
Classifier: Operating System :: Microsoft :: Windows
Classifier: Programming Language :: Python :: 3
Requires-Python: >=3.7
Requires-Dist: chime; platform_system != 'Windows'
Requires-Dist: pywin32; platform_system == 'Windows'
